{
    "key": "group_60523fe21a8f6",
    "title": "[Theme] Theme Settings",
    "fields": [
        {
            "key": "field_60523ff2928cf",
            "label": "Contact Info",
            "name": "",
            "type": "tab",
            "instructions": "",
            "required": 0,
            "conditional_logic": 0,
            "wrapper": {
                "width": "",
                "class": "",
                "id": ""
            },
            "placement": "top",
            "endpoint": 0
        },
        {
            "key": "field_60523ffd928d0",
            "label": "Address",
            "name": "address",
            "type": "wysiwyg",
            "instructions": "",
            "required": 0,
            "conditional_logic": 0,
            "wrapper": {
                "width": "",
                "class": "",
                "id": ""
            },
            "default_value": "",
            "tabs": "all",
            "toolbar": "full",
            "media_upload": 1,
            "delay": 0
        },
        {
            "key": "field_631250db7f236",
            "label": "Phone Type 1",
            "name": "phone_type_1",
            "type": "text",
            "instructions": "",
            "required": 0,
            "conditional_logic": 0,
            "wrapper": {
                "width": "",
                "class": "",
                "id": ""
            },
            "default_value": "",
            "placeholder": "",
            "prepend": "",
            "append": "",
            "maxlength": ""
        },
        {
            "key": "field_60524003928d1",
            "label": "Phone",
            "name": "phone",
            "type": "text",
            "instructions": "",
            "required": 0,
            "conditional_logic": 0,
            "wrapper": {
                "width": "",
                "class": "",
                "id": ""
            },
            "default_value": "",
            "placeholder": "",
            "prepend": "",
            "append": "",
            "maxlength": ""
        },
        {
            "key": "field_631251187f237",
            "label": "Phone Type 2",
            "name": "phone_type_2",
            "type": "text",
            "instructions": "",
            "required": 0,
            "conditional_logic": 0,
            "wrapper": {
                "width": "",
                "class": "",
                "id": ""
            },
            "default_value": "",
            "placeholder": "",
            "prepend": "",
            "append": "",
            "maxlength": ""
        },
        {
            "key": "field_63124a5c380fc",
            "label": "Tech Support Phone",
            "name": "tech_support_phone",
            "type": "text",
            "instructions": "",
            "required": 0,
            "conditional_logic": 0,
            "wrapper": {
                "width": "",
                "class": "",
                "id": ""
            },
            "default_value": "",
            "placeholder": "",
            "prepend": "",
            "append": "",
            "maxlength": ""
        },
        {
            "key": "field_60524019928d2",
            "label": "Email",
            "name": "email",
            "type": "email",
            "instructions": "",
            "required": 0,
            "conditional_logic": 0,
            "wrapper": {
                "width": "",
                "class": "",
                "id": ""
            },
            "default_value": "",
            "placeholder": "",
            "prepend": "",
            "append": ""
        },
        {
            "key": "field_6052402a928d3",
            "label": "Social Media",
            "name": "",
            "type": "tab",
            "instructions": "",
            "required": 0,
            "conditional_logic": 0,
            "wrapper": {
                "width": "",
                "class": "",
                "id": ""
            },
            "placement": "top",
            "endpoint": 0
        },
        {
            "key": "field_60524034928d4",
            "label": "Facebook",
            "name": "facebook",
            "type": "url",
            "instructions": "",
            "required": 0,
            "conditional_logic": 0,
            "wrapper": {
                "width": "",
                "class": "",
                "id": ""
            },
            "default_value": "",
            "placeholder": ""
        },
        {
            "key": "field_60524040928d5",
            "label": "Twitter",
            "name": "twitter",
            "type": "url",
            "instructions": "",
            "required": 0,
            "conditional_logic": 0,
            "wrapper": {
                "width": "",
                "class": "",
                "id": ""
            },
            "default_value": "",
            "placeholder": ""
        },
        {
            "key": "field_60524044928d6",
            "label": "Linkedin",
            "name": "linkedin",
            "type": "url",
            "instructions": "",
            "required": 0,
            "conditional_logic": 0,
            "wrapper": {
                "width": "",
                "class": "",
                "id": ""
            },
            "default_value": "",
            "placeholder": ""
        },
        {
            "key": "field_6140a0c2e11a4",
            "label": "Instagram",
            "name": "instagram",
            "type": "url",
            "instructions": "",
            "required": 0,
            "conditional_logic": 0,
            "wrapper": {
                "width": "",
                "class": "",
                "id": ""
            },
            "default_value": "",
            "placeholder": ""
        },
        {
            "key": "field_6052404a928d7",
            "label": "Youtube",
            "name": "youtube",
            "type": "url",
            "instructions": "",
            "required": 0,
            "conditional_logic": 0,
            "wrapper": {
                "width": "",
                "class": "",
                "id": ""
            },
            "default_value": "",
            "placeholder": ""
        },
        {
            "key": "field_60524080928d8",
            "label": "Media Assets",
            "name": "",
            "type": "tab",
            "instructions": "",
            "required": 0,
            "conditional_logic": 0,
            "wrapper": {
                "width": "",
                "class": "",
                "id": ""
            },
            "placement": "top",
            "endpoint": 0
        },
        {
            "key": "field_60524094928d9",
            "label": "Logo",
            "name": "logo",
            "type": "image",
            "instructions": "",
            "required": 0,
            "conditional_logic": 0,
            "wrapper": {
                "width": "",
                "class": "",
                "id": ""
            },
            "return_format": "id",
            "preview_size": "medium",
            "library": "all",
            "min_width": "",
            "min_height": "",
            "min_size": "",
            "max_width": "",
            "max_height": "",
            "max_size": "",
            "mime_types": ""
        },
        {
            "key": "field_606c974023c60",
            "label": "Placeholder Image",
            "name": "placeholder_image",
            "type": "image",
            "instructions": "",
            "required": 0,
            "conditional_logic": 0,
            "wrapper": {
                "width": "",
                "class": "",
                "id": ""
            },
            "return_format": "id",
            "preview_size": "medium",
            "library": "all",
            "min_width": "",
            "min_height": "",
            "min_size": "",
            "max_width": "",
            "max_height": "",
            "max_size": "",
            "mime_types": ""
        },
        {
            "key": "field_61409bf8ad37a",
            "label": "Footer",
            "name": "",
            "type": "tab",
            "instructions": "",
            "required": 0,
            "conditional_logic": 0,
            "wrapper": {
                "width": "",
                "class": "",
                "id": ""
            },
            "placement": "top",
            "endpoint": 0
        },
        {
            "key": "field_61409c03ad37b",
            "label": "Privacy Policy",
            "name": "privacy_policy",
            "type": "url",
            "instructions": "",
            "required": 0,
            "conditional_logic": 0,
            "wrapper": {
                "width": "",
                "class": "",
                "id": ""
            },
            "default_value": "",
            "placeholder": ""
        },
        {
            "key": "field_61409c0ead37c",
            "label": "Terms of Use",
            "name": "terms_of_use",
            "type": "url",
            "instructions": "",
            "required": 0,
            "conditional_logic": 0,
            "wrapper": {
                "width": "",
                "class": "",
                "id": ""
            },
            "default_value": "",
            "placeholder": ""
        },
        {
            "key": "field_61409c17ad37d",
            "label": "Sitemap",
            "name": "sitemap",
            "type": "url",
            "instructions": "",
            "required": 0,
            "conditional_logic": 0,
            "wrapper": {
                "width": "",
                "class": "",
                "id": ""
            },
            "default_value": "",
            "placeholder": ""
        },
        {
            "key": "field_61409c22ad37e",
            "label": "Site Credits",
            "name": "site_credits",
            "type": "url",
            "instructions": "",
            "required": 0,
            "conditional_logic": 0,
            "wrapper": {
                "width": "",
                "class": "",
                "id": ""
            },
            "default_value": "",
            "placeholder": ""
        },
        {
            "key": "field_615edbba93a55",
            "label": "Join Newsletter Action",
            "name": "join_newsletter_action",
            "type": "group",
            "instructions": "",
            "required": 0,
            "conditional_logic": 0,
            "wrapper": {
                "width": "",
                "class": "",
                "id": ""
            },
            "layout": "block",
            "sub_fields": [
                {
                    "key": "field_615edbe893a56",
                    "label": "Link or Popup?",
                    "name": "link_or_popup",
                    "type": "radio",
                    "instructions": "",
                    "required": 0,
                    "conditional_logic": 0,
                    "wrapper": {
                        "width": "",
                        "class": "",
                        "id": ""
                    },
                    "choices": {
                        "link": "Link",
                        "popup": "PopUp"
                    },
                    "allow_null": 0,
                    "other_choice": 0,
                    "default_value": "",
                    "layout": "vertical",
                    "return_format": "value",
                    "save_other_choice": 0
                },
                {
                    "key": "field_61409cb3659a0",
                    "label": "Join NewsLetter Link",
                    "name": "join_newsletter_link",
                    "type": "url",
                    "instructions": "",
                    "required": 0,
                    "conditional_logic": [
                        [
                            {
                                "field": "field_615edbe893a56",
                                "operator": "==",
                                "value": "link"
                            }
                        ]
                    ],
                    "wrapper": {
                        "width": "",
                        "class": "",
                        "id": ""
                    },
                    "default_value": "",
                    "placeholder": ""
                },
                {
                    "key": "field_615edc2493a57",
                    "label": "PopUp Content",
                    "name": "popup_content",
                    "type": "wysiwyg",
                    "instructions": "",
                    "required": 0,
                    "conditional_logic": [
                        [
                            {
                                "field": "field_615edbe893a56",
                                "operator": "==",
                                "value": "popup"
                            }
                        ]
                    ],
                    "wrapper": {
                        "width": "",
                        "class": "",
                        "id": ""
                    },
                    "default_value": "",
                    "tabs": "all",
                    "toolbar": "full",
                    "media_upload": 1,
                    "delay": 0
                }
            ]
        },
        {
            "key": "field_6241be983dab6",
            "label": "Join Our Newsletter - Button Label",
            "name": "join_our_newsletter_button_label",
            "type": "text",
            "instructions": "",
            "required": 0,
            "conditional_logic": 0,
            "wrapper": {
                "width": "",
                "class": "",
                "id": ""
            },
            "default_value": "",
            "placeholder": "Join Our Newsletter",
            "prepend": "",
            "append": "",
            "maxlength": ""
        },
        {
            "key": "field_615f9a108f540",
            "label": "Tracker Code",
            "name": "tracker_code",
            "type": "textarea",
            "instructions": "This field will hold the code,scripts to be hook in footer.",
            "required": 0,
            "conditional_logic": 0,
            "wrapper": {
                "width": "",
                "class": "",
                "id": ""
            },
            "default_value": "",
            "placeholder": "",
            "maxlength": "",
            "rows": 11,
            "new_lines": ""
        },
        {
            "key": "field_6140a28a43be1",
            "label": "Header",
            "name": "",
            "type": "tab",
            "instructions": "",
            "required": 0,
            "conditional_logic": 0,
            "wrapper": {
                "width": "",
                "class": "",
                "id": ""
            },
            "placement": "top",
            "endpoint": 0
        },
        {
            "key": "field_6241bd4a3dab5",
            "label": "Schedule Demo - Button Label",
            "name": "schedule_demo_button_label",
            "type": "text",
            "instructions": "",
            "required": 0,
            "conditional_logic": 0,
            "wrapper": {
                "width": "",
                "class": "",
                "id": ""
            },
            "default_value": "",
            "placeholder": "Schedule a Demo",
            "prepend": "",
            "append": "",
            "maxlength": ""
        },
        {
            "key": "field_6140a29043be2",
            "label": "Schedule demo Link",
            "name": "schedule_demo_link",
            "type": "url",
            "instructions": "",
            "required": 0,
            "conditional_logic": 0,
            "wrapper": {
                "width": "",
                "class": "",
                "id": ""
            },
            "default_value": "",
            "placeholder": ""
        },
        {
            "key": "field_614c56abcd968",
            "label": "404 Page",
            "name": "",
            "type": "tab",
            "instructions": "",
            "required": 0,
            "conditional_logic": 0,
            "wrapper": {
                "width": "",
                "class": "",
                "id": ""
            },
            "placement": "top",
            "endpoint": 0
        },
        {
            "key": "field_614c56c5cd969",
            "label": "404 Leads",
            "name": "page_404_leads",
            "type": "repeater",
            "instructions": "",
            "required": 0,
            "conditional_logic": 0,
            "wrapper": {
                "width": "",
                "class": "",
                "id": ""
            },
            "collapsed": "",
            "min": 0,
            "max": 4,
            "layout": "block",
            "button_label": "",
            "sub_fields": [
                {
                    "key": "field_614c57bacd96a",
                    "label": "Featured Image",
                    "name": "featured_image",
                    "type": "image",
                    "instructions": "",
                    "required": 0,
                    "conditional_logic": 0,
                    "wrapper": {
                        "width": "",
                        "class": "",
                        "id": ""
                    },
                    "return_format": "id",
                    "preview_size": "medium",
                    "library": "all",
                    "min_width": "",
                    "min_height": "",
                    "min_size": "",
                    "max_width": "",
                    "max_height": "",
                    "max_size": "",
                    "mime_types": ""
                },
                {
                    "key": "field_614c57d1cd96b",
                    "label": "Title",
                    "name": "title",
                    "type": "text",
                    "instructions": "",
                    "required": 0,
                    "conditional_logic": 0,
                    "wrapper": {
                        "width": "",
                        "class": "",
                        "id": ""
                    },
                    "default_value": "",
                    "placeholder": "",
                    "prepend": "",
                    "append": "",
                    "maxlength": ""
                },
                {
                    "key": "field_614c57d9cd96c",
                    "label": "Link",
                    "name": "link",
                    "type": "url",
                    "instructions": "",
                    "required": 0,
                    "conditional_logic": 0,
                    "wrapper": {
                        "width": "",
                        "class": "",
                        "id": ""
                    },
                    "default_value": "",
                    "placeholder": ""
                }
            ]
        },
        {
            "key": "field_614c7137fac64",
            "label": "Contact Us Link",
            "name": "contact_us_link",
            "type": "url",
            "instructions": "",
            "required": 0,
            "conditional_logic": 0,
            "wrapper": {
                "width": "",
                "class": "",
                "id": ""
            },
            "default_value": "",
            "placeholder": ""
        },
        {
            "key": "field_61545120a4fc0",
            "label": "Blog Main Page",
            "name": "",
            "type": "tab",
            "instructions": "",
            "required": 0,
            "conditional_logic": 0,
            "wrapper": {
                "width": "",
                "class": "",
                "id": ""
            },
            "placement": "top",
            "endpoint": 0
        },
        {
            "key": "field_6153e0e924288",
            "label": "Call to Action",
            "name": "blog_call_to_action__footer",
            "type": "flexible_content",
            "instructions": "For this field, this will only show at the bottom before the footer on blog main page!",
            "required": 0,
            "conditional_logic": 0,
            "wrapper": {
                "width": "",
                "class": "",
                "id": ""
            },
            "layouts": {
                "layout_6153e0f743a24": {
                    "key": "layout_6153e0f743a24",
                    "name": "5050_cta",
                    "label": "50\/50 CTA",
                    "display": "block",
                    "sub_fields": [
                        {
                            "key": "field_6153e1ad3f88d",
                            "label": "Call To Action - Left",
                            "name": "call_to_action_left",
                            "type": "group",
                            "instructions": "",
                            "required": 0,
                            "conditional_logic": 0,
                            "wrapper": {
                                "width": "",
                                "class": "",
                                "id": ""
                            },
                            "layout": "block",
                            "sub_fields": [
                                {
                                    "key": "field_6153e1ad7cb15",
                                    "label": "Title",
                                    "name": "title",
                                    "type": "text",
                                    "instructions": "",
                                    "required": 0,
                                    "conditional_logic": 0,
                                    "wrapper": {
                                        "width": "",
                                        "class": "",
                                        "id": ""
                                    },
                                    "default_value": "",
                                    "placeholder": "",
                                    "prepend": "",
                                    "append": "",
                                    "maxlength": ""
                                },
                                {
                                    "key": "field_6153e1ad7cb53",
                                    "label": "Content",
                                    "name": "content",
                                    "type": "wysiwyg",
                                    "instructions": "",
                                    "required": 0,
                                    "conditional_logic": 0,
                                    "wrapper": {
                                        "width": "",
                                        "class": "",
                                        "id": ""
                                    },
                                    "default_value": "",
                                    "tabs": "all",
                                    "toolbar": "full",
                                    "media_upload": 1,
                                    "delay": 0
                                },
                                {
                                    "key": "field_6153e1ad7cb8d",
                                    "label": "CTA Link",
                                    "name": "cta_link",
                                    "type": "link",
                                    "instructions": "",
                                    "required": 0,
                                    "conditional_logic": 0,
                                    "wrapper": {
                                        "width": "",
                                        "class": "",
                                        "id": ""
                                    },
                                    "return_format": ""
                                }
                            ]
                        },
                        {
                            "key": "field_6153e1ad3f8cc",
                            "label": "Call To Action - Right",
                            "name": "call_to_action_right",
                            "type": "group",
                            "instructions": "",
                            "required": 0,
                            "conditional_logic": 0,
                            "wrapper": {
                                "width": "",
                                "class": "",
                                "id": ""
                            },
                            "layout": "block",
                            "sub_fields": [
                                {
                                    "key": "field_6153e1ae9df07",
                                    "label": "Title",
                                    "name": "title",
                                    "type": "text",
                                    "instructions": "",
                                    "required": 0,
                                    "conditional_logic": 0,
                                    "wrapper": {
                                        "width": "",
                                        "class": "",
                                        "id": ""
                                    },
                                    "default_value": "",
                                    "placeholder": "",
                                    "prepend": "",
                                    "append": "",
                                    "maxlength": ""
                                },
                                {
                                    "key": "field_6153e1ae9df46",
                                    "label": "Content",
                                    "name": "content",
                                    "type": "wysiwyg",
                                    "instructions": "",
                                    "required": 0,
                                    "conditional_logic": 0,
                                    "wrapper": {
                                        "width": "",
                                        "class": "",
                                        "id": ""
                                    },
                                    "default_value": "",
                                    "tabs": "all",
                                    "toolbar": "full",
                                    "media_upload": 1,
                                    "delay": 0
                                },
                                {
                                    "key": "field_6153e1ae9df80",
                                    "label": "CTA Link",
                                    "name": "cta_link",
                                    "type": "link",
                                    "instructions": "",
                                    "required": 0,
                                    "conditional_logic": 0,
                                    "wrapper": {
                                        "width": "",
                                        "class": "",
                                        "id": ""
                                    },
                                    "return_format": "array"
                                }
                            ]
                        }
                    ],
                    "min": "",
                    "max": ""
                },
                "layout_6153e26ae1a3f": {
                    "key": "layout_6153e26ae1a3f",
                    "name": "attention_block",
                    "label": "Attention Block",
                    "display": "block",
                    "sub_fields": [
                        {
                            "key": "field_6153e254a9ba0",
                            "label": "Select Background",
                            "name": "select_background",
                            "type": "select",
                            "instructions": "",
                            "required": 0,
                            "conditional_logic": 0,
                            "wrapper": {
                                "width": "",
                                "class": "",
                                "id": ""
                            },
                            "choices": {
                                "white": "White",
                                "gray": "Gray"
                            },
                            "default_value": "white",
                            "allow_null": 0,
                            "multiple": 0,
                            "ui": 0,
                            "ajax": 0,
                            "return_format": "value",
                            "placeholder": ""
                        },
                        {
                            "key": "field_6153e254a9bdf",
                            "label": "Attention Block Content",
                            "name": "attention_block_content",
                            "type": "wysiwyg",
                            "instructions": "",
                            "required": 0,
                            "conditional_logic": 0,
                            "wrapper": {
                                "width": "",
                                "class": "",
                                "id": ""
                            },
                            "default_value": "",
                            "tabs": "all",
                            "toolbar": "full",
                            "media_upload": 1,
                            "delay": 0
                        }
                    ],
                    "min": "",
                    "max": ""
                },
                "layout_6153e3294e43c": {
                    "key": "layout_6153e3294e43c",
                    "name": "full_width_cta",
                    "label": "Full Width CTA",
                    "display": "block",
                    "sub_fields": [
                        {
                            "key": "field_6153e2c687cd0",
                            "label": "Full Width CTA Content",
                            "name": "full_width_cta_content",
                            "type": "wysiwyg",
                            "instructions": "This block will have a blue patterned background and a rainbow bottom border",
                            "required": 0,
                            "conditional_logic": 0,
                            "wrapper": {
                                "width": "",
                                "class": "",
                                "id": ""
                            },
                            "default_value": "",
                            "tabs": "all",
                            "toolbar": "full",
                            "media_upload": 1,
                            "delay": 0
                        }
                    ],
                    "min": "",
                    "max": ""
                }
            },
            "button_label": "Add Row",
            "min": "",
            "max": ""
        },
        {
            "key": "field_6155a42a1c323",
            "label": "Case Study Main Page",
            "name": "",
            "type": "tab",
            "instructions": "",
            "required": 0,
            "conditional_logic": 0,
            "wrapper": {
                "width": "",
                "class": "",
                "id": ""
            },
            "placement": "top",
            "endpoint": 0
        },
        {
            "key": "field_6155a45c1c324",
            "label": "Call to Action",
            "name": "case_study_call_to_action__footer",
            "type": "flexible_content",
            "instructions": "For this field, this will only show at the bottom before the footer on case study main page!",
            "required": 0,
            "conditional_logic": 0,
            "wrapper": {
                "width": "",
                "class": "",
                "id": ""
            },
            "layouts": {
                "layout_6153e0f743a24": {
                    "key": "layout_6153e0f743a24",
                    "name": "5050_cta",
                    "label": "50\/50 CTA",
                    "display": "block",
                    "sub_fields": [
                        {
                            "key": "field_6155a45c1c325",
                            "label": "Call To Action - Left",
                            "name": "call_to_action_left",
                            "type": "group",
                            "instructions": "",
                            "required": 0,
                            "conditional_logic": 0,
                            "wrapper": {
                                "width": "",
                                "class": "",
                                "id": ""
                            },
                            "layout": "block",
                            "sub_fields": [
                                {
                                    "key": "field_6155a45c1c326",
                                    "label": "Title",
                                    "name": "title",
                                    "type": "text",
                                    "instructions": "",
                                    "required": 0,
                                    "conditional_logic": 0,
                                    "wrapper": {
                                        "width": "",
                                        "class": "",
                                        "id": ""
                                    },
                                    "default_value": "",
                                    "placeholder": "",
                                    "prepend": "",
                                    "append": "",
                                    "maxlength": ""
                                },
                                {
                                    "key": "field_6155a45c1c327",
                                    "label": "Content",
                                    "name": "content",
                                    "type": "wysiwyg",
                                    "instructions": "",
                                    "required": 0,
                                    "conditional_logic": 0,
                                    "wrapper": {
                                        "width": "",
                                        "class": "",
                                        "id": ""
                                    },
                                    "default_value": "",
                                    "tabs": "all",
                                    "toolbar": "full",
                                    "media_upload": 1,
                                    "delay": 0
                                },
                                {
                                    "key": "field_6155a45c1c328",
                                    "label": "CTA Link",
                                    "name": "cta_link",
                                    "type": "link",
                                    "instructions": "",
                                    "required": 0,
                                    "conditional_logic": 0,
                                    "wrapper": {
                                        "width": "",
                                        "class": "",
                                        "id": ""
                                    },
                                    "return_format": "array"
                                }
                            ]
                        },
                        {
                            "key": "field_6155a45c1c329",
                            "label": "Call To Action - Right",
                            "name": "call_to_action_right",
                            "type": "group",
                            "instructions": "",
                            "required": 0,
                            "conditional_logic": 0,
                            "wrapper": {
                                "width": "",
                                "class": "",
                                "id": ""
                            },
                            "layout": "block",
                            "sub_fields": [
                                {
                                    "key": "field_6155a45c1c32a",
                                    "label": "Title",
                                    "name": "title",
                                    "type": "text",
                                    "instructions": "",
                                    "required": 0,
                                    "conditional_logic": 0,
                                    "wrapper": {
                                        "width": "",
                                        "class": "",
                                        "id": ""
                                    },
                                    "default_value": "",
                                    "placeholder": "",
                                    "prepend": "",
                                    "append": "",
                                    "maxlength": ""
                                },
                                {
                                    "key": "field_6155a45c1c32b",
                                    "label": "Content",
                                    "name": "content",
                                    "type": "wysiwyg",
                                    "instructions": "",
                                    "required": 0,
                                    "conditional_logic": 0,
                                    "wrapper": {
                                        "width": "",
                                        "class": "",
                                        "id": ""
                                    },
                                    "default_value": "",
                                    "tabs": "all",
                                    "toolbar": "full",
                                    "media_upload": 1,
                                    "delay": 0
                                },
                                {
                                    "key": "field_6155a45c1c32c",
                                    "label": "CTA Link",
                                    "name": "cta_link",
                                    "type": "link",
                                    "instructions": "",
                                    "required": 0,
                                    "conditional_logic": 0,
                                    "wrapper": {
                                        "width": "",
                                        "class": "",
                                        "id": ""
                                    },
                                    "return_format": "array"
                                }
                            ]
                        }
                    ],
                    "min": "",
                    "max": ""
                },
                "layout_6153e26ae1a3f": {
                    "key": "layout_6153e26ae1a3f",
                    "name": "attention_block",
                    "label": "Attention Block",
                    "display": "block",
                    "sub_fields": [
                        {
                            "key": "field_6155a45c1c32d",
                            "label": "Select Background",
                            "name": "select_background",
                            "type": "select",
                            "instructions": "",
                            "required": 0,
                            "conditional_logic": 0,
                            "wrapper": {
                                "width": "",
                                "class": "",
                                "id": ""
                            },
                            "choices": {
                                "white": "White",
                                "gray": "Gray"
                            },
                            "default_value": "white",
                            "allow_null": 0,
                            "multiple": 0,
                            "ui": 0,
                            "ajax": 0,
                            "return_format": "value",
                            "placeholder": ""
                        },
                        {
                            "key": "field_6155a45c1c32e",
                            "label": "Attention Block Content",
                            "name": "attention_block_content",
                            "type": "wysiwyg",
                            "instructions": "",
                            "required": 0,
                            "conditional_logic": 0,
                            "wrapper": {
                                "width": "",
                                "class": "",
                                "id": ""
                            },
                            "default_value": "",
                            "tabs": "all",
                            "toolbar": "full",
                            "media_upload": 1,
                            "delay": 0
                        }
                    ],
                    "min": "",
                    "max": ""
                },
                "layout_6153e3294e43c": {
                    "key": "layout_6153e3294e43c",
                    "name": "full_width_cta",
                    "label": "Full Width CTA",
                    "display": "block",
                    "sub_fields": [
                        {
                            "key": "field_6155a45c1c32f",
                            "label": "Full Width CTA Content",
                            "name": "full_width_cta_content",
                            "type": "wysiwyg",
                            "instructions": "This block will have a blue patterned background and a rainbow bottom border",
                            "required": 0,
                            "conditional_logic": 0,
                            "wrapper": {
                                "width": "",
                                "class": "",
                                "id": ""
                            },
                            "default_value": "",
                            "tabs": "all",
                            "toolbar": "full",
                            "media_upload": 1,
                            "delay": 0
                        }
                    ],
                    "min": "",
                    "max": ""
                }
            },
            "button_label": "Add Row",
            "min": "",
            "max": ""
        }
    ],
    "location": [
        [
            {
                "param": "options_page",
                "operator": "==",
                "value": "theme-general-settings"
            }
        ]
    ],
    "menu_order": 0,
    "position": "normal",
    "style": "default",
    "label_placement": "top",
    "instruction_placement": "label",
    "hide_on_screen": "",
    "active": true,
    "description": "",
    "show_in_rest": 0,
    "modified": 1662144897
}